PyDeepLib/__init__.py
PyDeepLib/colors.py
shamhyper-0.0.1.dist-info/METADATA
shamhyper-0.0.1.dist-info/WHEEL
shamhyper-0.0.1.dist-info/top_level.txt
shamhyper-0.0.1.dist-info/RECORD
